firemember/__init__.py
firemember/enc.py
firemember/help.py
firemember/lisensi.py
firemember-1.0.0.dist-info/METADATA
firemember-1.0.0.dist-info/WHEEL
firemember-1.0.0.dist-info/top_level.txt
firemember-1.0.0.dist-info/RECORD
